orange3_bcaats-0.2.4.dist-info/licenses/LICENSE
orangecontrib/__init__.py
orangecontrib/bcaats/__init__.py
orangecontrib/bcaats/_meta_extractors.py
orangecontrib/bcaats/widgets/__init__.py
orangecontrib/bcaats/widgets/ow_benfords_law.py
orangecontrib/bcaats/widgets/ow_color_table.py
orangecontrib/bcaats/widgets/ow_follow_the_money.py
orangecontrib/bcaats/widgets/ow_fuzzy_duplicate.py
orangecontrib/bcaats/widgets/ow_head_tail_exporter.py
orangecontrib/bcaats/widgets/ow_head_tail_reader.py
orangecontrib/bcaats/widgets/ow_metadata_extractor.py
orangecontrib/bcaats/widgets/ow_news_extractor.py
orangecontrib/bcaats/widgets/ow_sequence_checker.py
orangecontrib/bcaats/widgets/icons/addon_icon.png
orangecontrib/bcaats/widgets/icons/bendford.png
orangecontrib/bcaats/widgets/icons/color_table.png
orangecontrib/bcaats/widgets/icons/file_head.png
orangecontrib/bcaats/widgets/icons/follow_money.png
orangecontrib/bcaats/widgets/icons/fuzzy.png
orangecontrib/bcaats/widgets/icons/meta_extract.png
orangecontrib/bcaats/widgets/icons/scrape.png
orangecontrib/bcaats/widgets/icons/sequence.png
orange3_bcaats-0.2.4.dist-info/METADATA
orange3_bcaats-0.2.4.dist-info/WHEEL
orange3_bcaats-0.2.4.dist-info/entry_points.txt
orange3_bcaats-0.2.4.dist-info/top_level.txt
orange3_bcaats-0.2.4.dist-info/RECORD
