Metadata-Version: 2.4
Name: orange3-bcaats
Version: 0.2.4
Summary: BCAATs – Add-on Orange Data Mining Computer Assisted Audit Techniques (CAATs)
Author-email: Devi Ardiana <deviardn@gmail.com>
License: MIT
Project-URL: Homepage, https://github.com/deviardn/orange3-bcaats
Classifier: Programming Language :: Python :: 3
Classifier: License :: OSI Approved :: MIT License
Classifier: Operating System :: OS Independent
Requires-Python: >=3.9
License-File: LICENSE
Requires-Dist: orange3>=3.36.0
Requires-Dist: pandas>=1.5.0
Requires-Dist: numpy>=1.22.0
Requires-Dist: rapidfuzz>=3.0.0
Requires-Dist: openpyxl>=3.1.0
Requires-Dist: Pillow>=10.0
Requires-Dist: PyPDF2>=3.0
Requires-Dist: mutagen>=1.47
Requires-Dist: python-magic>=0.4; sys_platform != "win32"
Requires-Dist: python-magic-bin>=0.4; sys_platform == "win32"
Requires-Dist: newspaper3k>=0.2.8
Requires-Dist: lxml_html_clean>=0.1.0
Requires-Dist: sumy>=0.11
Dynamic: license-file
